simplesqlitewrap/__init__.py
simplesqlitewrap-0.1.15.dist-info/METADATA
simplesqlitewrap-0.1.15.dist-info/RECORD
simplesqlitewrap-0.1.15.dist-info/WHEEL
simplesqlitewrap-0.1.15.dist-info/top_level.txt
