Metadata-Version: 2.1
Name: simplesqlitewrap
Version: 0.1.15
Summary: Simple util from which I inherit my sqlite classes
Home-page: https://github.com/zeroone2numeral2/simplesqlitewrap
Author: zeroone2numeral2
License: MIT
Platform: UNKNOWN
Classifier: Programming Language :: Python :: 3
Classifier: License :: OSI Approved :: MIT License
Classifier: Operating System :: OS Independent
Classifier: Topic :: Database
